llama_index/llms/llamafile/__init__.py
llama_index/llms/llamafile/base.py
llama_index_llms_llamafile-0.4.1.dist-info/METADATA
llama_index_llms_llamafile-0.4.1.dist-info/WHEEL
llama_index_llms_llamafile-0.4.1.dist-info/licenses/LICENSE
llama_index_llms_llamafile-0.4.1.dist-info/RECORD
